quosc/__init__.py
quosc/full_calculation.py
quosc/utils.py
quosc/initialisation/__init__.py
quosc/initialisation/band_calc.py
quosc/initialisation/create_mesh.py
quosc/initialisation/load_data.py
quosc/plotting/__init__.py
quosc/plotting/energy_plots.py
quosc/slicing/__init__.py
quosc/slicing/extremal_orbits.py
quosc/slicing/group_sections.py
quosc/slicing/slice_mesh.py
quosc/torque_simulation/__init__.py
quosc/torque_simulation/grouping.py
quosc/torque_simulation/interpolation.py
quosc/torque_simulation/torque_simulation.py
quosc-0.4.3.dist-info/LICENSE
quosc-0.4.3.dist-info/METADATA
quosc-0.4.3.dist-info/WHEEL
quosc-0.4.3.dist-info/top_level.txt
quosc-0.4.3.dist-info/RECORD
