Metadata-Version: 2.2
Name: quosc
Version: 0.4.3
Summary: Simulating quantum oscillations
Home-page: https://github.com/mihirm2305/quosc
Author: Mihir Manium
License: MIT License
Classifier: Programming Language :: Python :: 3
Classifier: License :: OSI Approved :: MIT License
Classifier: Operating System :: OS Independent
Requires-Python: >=3.7
License-File: LICENSE
Requires-Dist: numpy
Requires-Dist: matplotlib
Requires-Dist: joblib
Requires-Dist: trimesh
Requires-Dist: scikit-image
Requires-Dist: scikit-learn
Requires-Dist: pandas
Requires-Dist: shapely
Requires-Dist: rtree
Requires-Dist: seaborn
Dynamic: home-page
